pyproject.toml
requirements-ci.txt
setup.cfg
docs/Makefile
docs/source/conf.py
docs/source/feast_spark.api.rst
docs/source/feast_spark.contrib.rst
docs/source/feast_spark.contrib.validation.rst
docs/source/feast_spark.pyspark.launchers.aws.rst
docs/source/feast_spark.pyspark.launchers.gcloud.rst
docs/source/feast_spark.pyspark.launchers.k8s.rst
docs/source/feast_spark.pyspark.launchers.rst
docs/source/feast_spark.pyspark.launchers.standalone.rst
docs/source/feast_spark.pyspark.rst
docs/source/feast_spark.rst
docs/source/feast_spark.third_party.grpc.health.rst
docs/source/feast_spark.third_party.grpc.health.v1.rst
docs/source/feast_spark.third_party.grpc.rst
docs/source/feast_spark.third_party.rst
docs/source/index.rst
docs/source/modules.rst
feast_spark/__init__.py
feast_spark/cli.py
feast_spark/client.py
feast_spark/constants.py
feast_spark/job_service.py
feast_spark/lock_manager.py
feast_spark/metrics.py
feast_spark/remote_job.py
feast_spark/api/JobService_pb2.py
feast_spark/api/JobService_pb2_grpc.py
feast_spark/api/__init__.py
feast_spark/contrib/__init__.py
feast_spark/contrib/validation/__init__.py
feast_spark/contrib/validation/base.py
feast_spark/contrib/validation/ge.py
feast_spark/pyspark/__init__.py
feast_spark/pyspark/abc.py
feast_spark/pyspark/historical_feature_retrieval_job.py
feast_spark/pyspark/launcher.py
feast_spark/pyspark/launchers/__init__.py
feast_spark/pyspark/launchers/aws/__init__.py
feast_spark/pyspark/launchers/aws/emr.py
feast_spark/pyspark/launchers/aws/emr_utils.py
feast_spark/pyspark/launchers/gcloud/__init__.py
feast_spark/pyspark/launchers/gcloud/dataproc.py
feast_spark/pyspark/launchers/k8s/__init__.py
feast_spark/pyspark/launchers/k8s/k8s.py
feast_spark/pyspark/launchers/k8s/k8s_utils.py
feast_spark/pyspark/launchers/standalone/__init__.py
feast_spark/pyspark/launchers/standalone/local.py
feast_spark/third_party/__init__.py
feast_spark/third_party/grpc/__init__.py
feast_spark/third_party/grpc/health/__init__.py
feast_spark.egg-info/PKG-INFO
feast_spark.egg-info/SOURCES.txt
feast_spark.egg-info/dependency_links.txt
feast_spark.egg-info/entry_points.txt
feast_spark.egg-info/requires.txt
feast_spark.egg-info/top_level.txt
feast_spark-0.2.37.dist-info/METADATA
feast_spark-0.2.37.dist-info/WHEEL
feast_spark-0.2.37.dist-info/entry_points.txt
feast_spark-0.2.37.dist-info/top_level.txt
feast_spark-0.2.37.dist-info/RECORD
