Metadata-Version: 2.1
Name: feast-spark
Version: 0.2.37
Summary: Spark extensions for Feast
Home-page: https://github.com/feast-dev/feast-spark
Author: Feast
License: Apache
Classifier: License :: OSI Approved :: Apache Software License
Classifier: Programming Language :: Python
Classifier: Programming Language :: Python :: 3
Classifier: Programming Language :: Python :: 3.6
Requires-Python: >=3.6.0
Requires-Dist: feast (<0.10.0,>=0.9.8)
Requires-Dist: Click (==7.*)
Requires-Dist: google-api-core (==1.22.4)
Requires-Dist: google-cloud-bigquery (==1.18.*)
Requires-Dist: google-cloud-storage (==1.20.*)
Requires-Dist: google-cloud-core (==1.0.*)
Requires-Dist: googleapis-common-protos (==1.52.*)
Requires-Dist: google-cloud-bigquery-storage (==0.7.*)
Requires-Dist: google-cloud-dataproc (==2.0.2)
Requires-Dist: kubernetes (==12.0.*)
Requires-Dist: grpcio-tools (==1.31.0)
Requires-Dist: mypy-protobuf (==2.5)
Requires-Dist: croniter (==1.*)
Requires-Dist: redis (==4.1.*)
Requires-Dist: pyarrow (==2.0.0)
Requires-Dist: pandas (>=1.0.5)
Requires-Dist: prometheus-client (==0.14.0)
Provides-Extra: dev
Requires-Dist: mypy-protobuf (==1.*) ; extra == 'dev'
Requires-Dist: grpcio-testing (==1.*) ; extra == 'dev'
Provides-Extra: validation
Requires-Dist: great-expectations (==0.13.2) ; extra == 'validation'
Requires-Dist: pyspark (==3.0.1) ; extra == 'validation'
